pylotable/__init__.py
pylotable/coprocessor.py
pylotable/win_coprocessor.py
pylotable-0.0.4.dist-info/licenses/LICENSE.md
pylotable-0.0.4.dist-info/METADATA
pylotable-0.0.4.dist-info/WHEEL
pylotable-0.0.4.dist-info/top_level.txt
pylotable-0.0.4.dist-info/RECORD
