Metadata-Version: 2.4
Name: pylotable
Version: 0.0.4
Summary: A simple data processing library and toolbox.
Author-email: Samuel Andrés <samuel.andres@yahoo.fr>
License: This is free and unencumbered software released into the public domain.
Project-URL: Homepage, https://github.com/SamuelAndresPascal/cosmoloj-py/tree/pylotable_0.0.4/pylotable
Project-URL: Documentation, http://cosmoloj.com/mkdocs/pylotable/0.0.4
Keywords: statistics,data,processing
Classifier: Programming Language :: Python :: 3
Classifier: Operating System :: OS Independent
Classifier: Development Status :: 5 - Production/Stable
Classifier: Intended Audience :: Developers
Classifier: Intended Audience :: Science/Research
Classifier: License :: Public Domain
Classifier: Topic :: Scientific/Engineering
Classifier: Topic :: Software Development
Classifier: Topic :: Utilities
Requires-Python: >=3.12
License-File: LICENSE.md
Requires-Dist: pandas
Dynamic: license-file
